dalle2/__init__.py
dalle2/dalle2.py
dalle2-1.0.11.dist-info/LICENSE
dalle2-1.0.11.dist-info/METADATA
dalle2-1.0.11.dist-info/WHEEL
dalle2-1.0.11.dist-info/top_level.txt
dalle2-1.0.11.dist-info/RECORD
