Metadata-Version: 2.1
Name: dalle2
Version: 1.0.11
Summary: Use DALL·E 2 in Python
Home-page: https://github.com/ezzcodeezzlife/dalle2-in-python
Author: ezzcodeezzlife
Author-email: author@example.com
Project-URL: Bug Tracker, https://github.com/ezzcodeezzlife/dalle2-in-python/issues
Classifier: Programming Language :: Python :: 3
Classifier: License :: OSI Approved :: MIT License
Classifier: Operating System :: OS Independent
Requires-Python: >=3.6
License-File: LICENSE
Requires-Dist: requests
